<?xml version="1.0"?>
<!DOCTYPE hibernate-mapping PUBLIC "-//Hibernate/Hibernate Mapping DTD 3.0//EN"
"http://www.hibernate.org/dtd/hibernate-mapping-3.0.dtd">
<!-- Generated Dec 16, 2016 10:52:23 AM by Hibernate Tools 4.3.1 -->
<hibernate-mapping>
    <class name="com.hrms.model.LoanEligibility" table="loan_eligibility" catalog="hrmsdp_10" optimistic-lock="version">
        <id name="eligibilityRuleId" type="int">
            <column name="eligibility_rule_id" />
            <generator class="assigned" />
        </id>
        <property name="flatAmtRate" type="java.lang.Integer">
            <column name="flat_amt_rate" />
        </property>
    </class>
</hibernate-mapping>
